s4s/__init__.py
s4s/__main__.py
s4s/s4s.py
s4s-1.0.3.dist-info/DESCRIPTION.rst
s4s-1.0.3.dist-info/METADATA
s4s-1.0.3.dist-info/RECORD
s4s-1.0.3.dist-info/WHEEL
s4s-1.0.3.dist-info/entry_points.txt
s4s-1.0.3.dist-info/metadata.json
s4s-1.0.3.dist-info/top_level.txt
