Metadata-Version: 2.0
Name: s4s
Version: 1.0.3
Summary: Service for Script
Home-page: https://github.com/Priezt/s4s
Author: Priezt
Author-email: UNKNOWN
License: MIT
Platform: UNKNOWN
Requires-Dist: flask
